example_pkg/__init__.py
SDK-1.0.0.dist-info/LICENSE
SDK-1.0.0.dist-info/METADATA
SDK-1.0.0.dist-info/WHEEL
SDK-1.0.0.dist-info/top_level.txt
SDK-1.0.0.dist-info/RECORD
