Metadata-Version: 2.1
Name: SDK
Version: 1.0.0
Summary: Unified data transmission interface
Home-page: https://github.com/pypa/sampleproject
Author: zhouruifu
Author-email: rocket_2014@126.com
License: UNKNOWN
Platform: UNKNOWN
Classifier: Programming Language :: Python :: 2
Classifier: License :: OSI Approved :: MIT License
Classifier: Operating System :: OS Independent
